[
  {
    "name": "createdAt",
    "fieldId": "createdAt",
    "componentId": "date",
    "options": {},
    "validations": {
      "required-field": {
        "value": true
      }
    },
    "fieldType": "date",
    "system": true,
    "defaultField": false,
    "modelId": "translations"
  },
  {
    "name": "updatedAt",
    "fieldId": "updatedAt",
    "componentId": "date",
    "options": {},
    "validations": {
      "required-field": {
        "value": true
      }
    },
    "fieldType": "date",
    "system": true,
    "defaultField": false,
    "modelId": "translations"
  },
  {
    "name": "ID",
    "fieldId": "ID",
    "componentId": "single-line-text",
    "options": {},
    "validations": {
      "required-field": {
        "value": true
      }
    },
    "fieldType": "string",
    "system": true,
    "defaultField": false,
    "modelId": "translations"
  },
  {
    "name": "status",
    "fieldId": "status",
    "componentId": "single-line-text",
    "options": {},
    "validations": {
      "required-field": {
        "value": true
      }
    },
    "fieldType": "string",
    "system": true,
    "defaultField": false,
    "modelId": "translations"
  },
  {
    "name": "key",
    "fieldId": "key",
    "modelId": "translations",
    "componentId": "single-line-text",
    "options": {},
    "validations": {},
    "fieldType": "string"
  },
  {
    "name": "value",
    "fieldId": "value",
    "modelId": "translations",
    "componentId": "single-line-text",
    "options": {
      "title-field": {
        "value": true
      }
    },
    "validations": {},
    "fieldType": "string"
  }
]